[
  {
    "name": "Basic",
    "icon": "creeper",
    "price": "$1.00",
    "firstMonthPrice": "$3.00",
    "period": "/quarter",
    "promoCode": "3UX37XLVPL",
    "promoDiscount": "15% First Month Discount",
    "orderLink": "https://my.expanse.host/index.php/store/discord-bots/basic",
    "features": [
      { "icon": "cpu", "text": "50% CPU (Ryzen 9 9950X)" },
      { "icon": "ram", "text": "512MB DDR5 RAM" },
      { "icon": "storage", "text": "5GB NVMe Storage" },
      { "icon": "shield", "text": "Unmanaged - Basic Support" },
      { "icon": "backup", "text": "Free Low Traffic IP", "included": false }
    ],
    "highlighted": false,
    "color": "text-blue-500",
    "borderColor": "border-blue-500",
    "bgColor": "bg-blue-500",
    "hoverBgColor": "hover:bg-blue-600",
    "glowColor": "59, 130, 246"
  },
  {
    "name": "Advanced",
    "icon": "zombie",
    "price": "$2.00",
    "firstMonthPrice": "$1.7",
    "period": "/month",
    "promoCode": "3UX37XLVPL",
    "promoDiscount": "15% First Month Discount",
    "orderLink": "https://my.expanse.host/index.php/store/discord-bots/advanced",
    "features": [
      { "icon": "cpu", "text": "75% CPU (Ryzen 9 9950X)" },
      { "icon": "ram", "text": "1GB DDR5 RAM" },
      { "icon": "storage", "text": "15GB NVMe Storage" },
      { "icon": "shield", "text": "Unmanaged - Basic Support" },
      { "icon": "backup", "text": "Free Low Traffic IP", "included": false }
    ],
    "highlighted": false,
    "color": "text-purple-500",
    "borderColor": "border-purple-500",
    "bgColor": "bg-purple-500",
    "hoverBgColor": "hover:bg-purple-600",
    "glowColor": "168, 85, 247"
  },
  {
    "name": "Professional",
    "icon": "enderman",
    "price": "$4.00",
    "firstMonthPrice": "$3.4",
    "period": "/month",
    "promoCode": "3UX37XLVPL",
    "promoDiscount": "15% First Month Discount",
    "orderLink": "https://my.expanse.host/index.php/store/discord-bots/professional",
    "features": [
      { "icon": "cpu", "text": "100% CPU (Ryzen 9 9950X)" },
      { "icon": "ram", "text": "3GB DDR5 RAM" },
      { "icon": "storage", "text": "40GB NVMe Storage" },
      { "icon": "shield", "text": "Unmanaged - Basic Support" },
      { "icon": "backup", "text": "Free Low Traffic IP", "included": false }
    ],
    "highlighted": false,
    "color": "text-indigo-500",
    "borderColor": "border-indigo-500",
    "bgColor": "bg-indigo-500",
    "hoverBgColor": "hover:bg-indigo-600",
    "glowColor": "99, 102, 241"
  },
  {
    "name": "Ultimate",
    "icon": "blaze",
    "price": "$10.00",
    "firstMonthPrice": "$8.5",
    "period": "/month",
    "promoCode": "3UX37XLVPL",
    "promoDiscount": "15% First Month Discount",
    "orderLink": "https://my.expanse.host/index.php/store/discord-bots/ultimate",
    "features": [
      { "icon": "cpu", "text": "300% CPU (Ryzen 9 9950X)" },
      { "icon": "ram", "text": "7GB DDR5 RAM" },
      { "icon": "storage", "text": "75GB NVMe Storage" },
      { "icon": "shield", "text": "Unmanaged - Basic Support" },
      { "icon": "backup", "text": "Free Low Traffic IP", "included": true }
    ],
    "highlighted": false,
    "color": "text-cyan-500",
    "borderColor": "border-cyan-500",
    "bgColor": "bg-cyan-500",
    "hoverBgColor": "hover:bg-cyan-600",
    "glowColor": "6, 182, 212"
  }
]
